urdubiometer/__init__.py
urdubiometer/cli.py
urdubiometer/urdubiometer.py
urdubiometer/data/messages.py
urdubiometer/data/messages/messages_en.py
urdubiometer/data/messages/messages_hi.py
urdubiometer/data/messages/messages_ur.py
urdubiometer/scanner/__init__.py
urdubiometer/scanner/ghazal.py
urdubiometer/scanner/initialize.py
urdubiometer/scanner/scanner.py
urdubiometer/scanner/types.py
urdubiometer/scanner/validate.py
urdubiometer/settings/constraints.yml
urdubiometer/settings/ghazal_meters.yml
urdubiometer/settings/long.yml
urdubiometer/settings/mir_meters.yml
urdubiometer/settings/short.yml
urdubiometer/settings/transcription.yml
urdubiometer-0.2.9.dist-info/AUTHORS.rst
urdubiometer-0.2.9.dist-info/LICENSE
urdubiometer-0.2.9.dist-info/METADATA
urdubiometer-0.2.9.dist-info/WHEEL
urdubiometer-0.2.9.dist-info/entry_points.txt
urdubiometer-0.2.9.dist-info/top_level.txt
urdubiometer-0.2.9.dist-info/RECORD
